[
  {
    "title": "🏎️ GP Australia, Melbourne",
    "location": "Albert Park Circuit, Melbourne, Australia",
    "geo_lat": -37.8497,
    "geo_lon": 144.9680,
    "url": "https://www.formula1.com/en/racing/2026/Australia.html",
    "broadcasters": ["DAZN F1"],
    "categories": ["F1", "Motorsport"],
    "status": "CONFIRMED",
    "description": "Ronda 1. El inicio de la temporada 2026 en el parque Albert Park.",
    "sessions": [
      {"name": "P1", "start": "2026-03-06T02:30:00Z", "end": "2026-03-06T03:30:00Z"},
      {"name": "P2", "start": "2026-03-06T06:00:00Z", "end": "2026-03-06T07:00:00Z"},
      {"name": "P3", "start": "2026-03-07T02:30:00Z", "end": "2026-03-07T03:30:00Z"},
      {"name": "Qualy", "start": "2026-03-07T06:00:00Z", "end": "2026-03-07T07:00:00Z"},
      {"name": "Carrera", "start": "2026-03-08T05:00:00Z", "end": "2026-03-08T07:00:00Z"}
    ]
  },
  {
    "title": "🏎️ GP de China, Shanghai - Sprint",
    "location": "Shanghai International Circuit, Shanghai, China",
    "geo_lat": 31.3389,
    "geo_lon": 121.2210,
    "url": "https://www.formula1.com/en/racing/2026/China.html",
    "broadcasters": ["DAZN F1", "Movistar+"],
    "categories": ["F1", "Sprint", "Motorsport"],
    "status": "CONFIRMED",
    "description": "Ronda 2. Formato Sprint en el inmenso circuito de Shanghai.",
    "sessions": [
      {"name": "P1", "start": "2026-03-13T04:30:00Z", "end": "2026-03-13T05:30:00Z"},
      {"name": "Sprint Qualy", "start": "2026-03-13T08:30:00Z", "end": "2026-03-13T09:14:00Z"},
      {"name": "Sprint", "start": "2026-03-14T04:00:00Z", "end": "2026-03-14T05:00:00Z"},
      {"name": "Qualy", "start": "2026-03-14T08:00:00Z", "end": "2026-03-14T09:00:00Z"},
      {"name": "Carrera", "start": "2026-03-15T08:00:00Z", "end": "2026-03-15T10:00:00Z"}
    ]
  },
  {
    "title": "🏎️ GP de Japón, Suzuka",
    "location": "Suzuka Circuit, Suzuka, Japan",
    "geo_lat": 34.8431,
    "geo_lon": 136.5410,
    "url": "https://www.formula1.com/en/racing/2026/Japan.html",
    "broadcasters": ["DAZN F1", "Movistar+"],
    "categories": ["F1", "Motorsport"],
    "status": "CONFIRMED",
    "description": "Ronda 3. Las curvas en S y la 130R esperan en uno de los circuitos más técnicos.",
    "sessions": [
      {"name": "P1", "start": "2026-03-27T03:30:00Z", "end": "2026-03-27T04:30:00Z"},
      {"name": "P2", "start": "2026-03-27T07:00:00Z", "end": "2026-03-27T08:00:00Z"},
      {"name": "P3", "start": "2026-03-28T03:30:00Z", "end": "2026-03-28T04:30:00Z"},
      {"name": "Qualy", "start": "2026-03-28T07:00:00Z", "end": "2026-03-28T08:00:00Z"},
      {"name": "Carrera", "start": "2026-03-29T07:00:00Z", "end": "2026-03-29T09:00:00Z"}
    ]
  },
  {
    "title": "🏎️ GP de Bahréin, Sakhir",
    "location": "Bahrain International Circuit, Sakhir, Bahrain",
    "geo_lat": 26.0325,
    "geo_lon": 50.5106,
    "url": "https://www.formula1.com/en/racing/2026/Bahrain.html",
    "broadcasters": ["DAZN F1", "Movistar+"],
    "categories": ["F1", "Motorsport"],
    "status": "CONFIRMED",
    "description": "Ronda 4. Carrera nocturna bajo los focos del desierto.",
    "sessions": [
      {"name": "P1", "start": "2026-04-10T13:30:00Z", "end": "2026-04-10T14:30:00Z"},
      {"name": "P2", "start": "2026-04-10T17:00:00Z", "end": "2026-04-10T18:00:00Z"},
      {"name": "P3", "start": "2026-04-11T14:30:00Z", "end": "2026-04-11T15:30:00Z"},
      {"name": "Qualy", "start": "2026-04-11T18:00:00Z", "end": "2026-04-11T19:00:00Z"},
      {"name": "Carrera", "start": "2026-04-12T17:00:00Z", "end": "2026-04-12T19:00:00Z"}
    ]
  },
  {
    "title": "🏎️ GP de Arabia Saudita, Jeddah",
    "location": "Jeddah Corniche Circuit, Jeddah, Saudi Arabia",
    "geo_lat": 21.6319,
    "geo_lon": 39.1044,
    "url": "https://www.formula1.com/en/racing/2026/Saudi_Arabia.html",
    "broadcasters": ["DAZN F1", "Movistar+"],
    "categories": ["F1", "Motorsport"],
    "status": "CONFIRMED",
    "description": "Ronda 5. El circuito callejero más rápido del mundo.",
    "sessions": [
      {"name": "P1", "start": "2026-04-17T15:30:00Z", "end": "2026-04-17T16:30:00Z"},
      {"name": "P2", "start": "2026-04-17T19:00:00Z", "end": "2026-04-17T20:00:00Z"},
      {"name": "P3", "start": "2026-04-18T15:30:00Z", "end": "2026-04-18T16:30:00Z"},
      {"name": "Qualy", "start": "2026-04-18T19:00:00Z", "end": "2026-04-18T20:00:00Z"},
      {"name": "Carrera", "start": "2026-04-19T19:00:00Z", "end": "2026-04-19T21:00:00Z"}
    ]
  },
  {
    "title": "🏎️ GP de Miami, Miami - Sprint",
    "location": "Miami International Autodrome, Miami, USA",
    "geo_lat": 25.9581,
    "geo_lon": -80.2389,
    "url": "https://www.formula1.com/en/racing/2026/Miami.html",
    "broadcasters": ["DAZN F1", "Movistar+"],
    "categories": ["F1", "Sprint", "Motorsport"],
    "status": "CONFIRMED",
    "description": "Ronda 6. Glamour y velocidad alrededor del Hard Rock Stadium.",
    "sessions": [
      {"name": "P1", "start": "2026-05-01T18:30:00Z", "end": "2026-05-01T19:30:00Z"},
      {"name": "Sprint Qualy", "start": "2026-05-01T22:30:00Z", "end": "2026-05-01T23:14:00Z"},
      {"name": "Sprint", "start": "2026-05-02T18:00:00Z", "end": "2026-05-02T19:00:00Z"},
      {"name": "Qualy", "start": "2026-05-02T22:00:00Z", "end": "2026-05-02T23:00:00Z"},
      {"name": "Carrera", "start": "2026-05-03T22:00:00Z", "end": "2026-05-04T00:00:00Z"}
    ]
  },
  {
    "title": "🏎️ GP de Canadá, Montreal - Sprint",
    "location": "Circuit Gilles Villeneuve, Montreal, Canada",
    "geo_lat": 45.5006,
    "geo_lon": -73.5228,
    "url": "https://www.formula1.com/en/racing/2026/Canada.html",
    "broadcasters": ["DAZN F1", "Movistar+"],
    "categories": ["F1", "Sprint", "Motorsport"],
    "status": "CONFIRMED",
    "description": "Ronda 7. El Muro de los Campeones espera en la Île Notre-Dame.",
    "sessions": [
      {"name": "P1", "start": "2026-05-22T18:30:00Z", "end": "2026-05-22T19:30:00Z"},
      {"name": "Sprint Qualy", "start": "2026-05-22T22:30:00Z", "end": "2026-05-22T23:14:00Z"},
      {"name": "Sprint", "start": "2026-05-23T18:00:00Z", "end": "2026-05-23T19:00:00Z"},
      {"name": "Qualy", "start": "2026-05-23T22:00:00Z", "end": "2026-05-23T23:00:00Z"},
      {"name": "Carrera", "start": "2026-05-24T22:00:00Z", "end": "2026-05-25T00:00:00Z"}
    ]
  },
  {
    "title": "🏎️ GP de Mónaco, Mónaco",
    "location": "Circuit de Monaco, Monte Carlo, Monaco",
    "geo_lat": 43.7347,
    "geo_lon": 7.4206,
    "url": "https://www.formula1.com/en/racing/2026/Monaco.html",
    "broadcasters": ["DAZN F1", "Movistar+"],
    "categories": ["F1", "Motorsport", "Classic"],
    "status": "CONFIRMED",
    "description": "Ronda 8. La joya de la corona, donde la clasificación es todo.",
    "sessions": [
      {"name": "P1", "start": "2026-06-05T13:30:00Z", "end": "2026-06-05T14:30:00Z"},
      {"name": "P2", "start": "2026-06-05T17:00:00Z", "end": "2026-06-05T18:00:00Z"},
      {"name": "P3", "start": "2026-06-06T12:30:00Z", "end": "2026-06-06T13:30:00Z"},
      {"name": "Qualy", "start": "2026-06-06T16:00:00Z", "end": "2026-06-06T17:00:00Z"},
      {"name": "Carrera", "start": "2026-06-07T15:00:00Z", "end": "2026-06-07T17:00:00Z"}
    ]
  },
  {
    "title": "🏎️ GP de España, Barcelona",
    "location": "Circuit de Barcelona-Catalunya, Montmeló, Spain",
    "geo_lat": 41.5700,
    "geo_lon": 2.2611,
    "url": "https://www.formula1.com/es/racing/2026/barcelona-catalunya.html",
    "broadcasters": ["DAZN F1", "Movistar+"],
    "categories": ["F1", "Motorsport"],
    "status": "CONFIRMED",
    "description": "Ronda 9. El clásico europeo y prueba definitiva para la aerodinámica.",
    "sessions": [
      { "name": "P1", "start": "2026-06-12T13:30:00Z", "end": "2026-06-12T14:30:00Z" },
      { "name": "P2", "start": "2026-06-12T17:00:00Z", "end": "2026-06-12T18:00:00Z" },
      { "name": "P3", "start": "2026-06-13T12:30:00Z", "end": "2026-06-13T13:30:00Z" },
      { "name": "Qualy", "start": "2026-06-13T16:00:00Z", "end": "2026-06-13T17:00:00Z" },
      { "name": "Carrera", "start": "2026-06-14T15:00:00Z", "end": "2026-06-14T17:00:00Z" }
    ]
  },
  {
    "title": "🏎️ GP de Austria, Spielberg",
    "location": "Red Bull Ring, Spielberg, Austria",
    "geo_lat": 47.2197,
    "geo_lon": 14.7647,
    "url": "https://www.formula1.com/en/racing/2026/Austria.html",
    "broadcasters": ["DAZN F1", "Movistar+"],
    "categories": ["F1", "Sprint", "Motorsport"],
    "status": "CONFIRMED",
    "description": "Ronda 10. Velocidad pura entre las montañas de Estiria.",
    "sessions": [
        { "name": "P1", "start": "2026-06-26T13:30:00Z", "end": "2026-06-26T14:30:00Z" },
        { "name": "P2", "start": "2026-06-26T17:00:00Z", "end": "2026-06-26T18:00:00Z" },
        { "name": "P3", "start": "2026-06-27T12:30:00Z", "end": "2026-06-27T13:30:00Z" },
        { "name": "Qualy", "start": "2026-06-27T16:00:00Z", "end": "2026-06-27T17:00:00Z" },
        { "name": "Carrera", "start": "2026-06-28T15:00:00Z", "end": "2026-06-28T17:00:00Z" }
    ]
  },
  {
    "title": "🏎️ GP de Reino Unido, Silverstone - Sprint",
    "location": "Silverstone Circuit, Silverstone, UK",
    "geo_lat": 52.0786,
    "geo_lon": -1.0169,
    "url": "https://www.formula1.com/en/racing/2026/Great_Britain.html",
    "broadcasters": ["DAZN F1", "Movistar+"],
    "categories": ["F1", "Sprint", "Motorsport", "Classic"],
    "status": "CONFIRMED",
    "description": "Ronda 11. La cuna de la F1 con formato Sprint.",
    "sessions": [
      { "name": "P1", "start": "2026-07-03T13:30:00Z", "end": "2026-07-03T14:30:00Z" },
      { "name": "Sprint Qualy", "start": "2026-07-03T17:30:00Z", "end": "2026-07-03T18:14:00Z" },
      { "name": "Sprint", "start": "2026-07-04T13:00:00Z", "end": "2026-07-04T14:00:00Z" },
      { "name": "Qualy", "start": "2026-07-04T17:00:00Z", "end": "2026-07-04T18:00:00Z" },
      { "name": "Carrera", "start": "2026-07-05T16:00:00Z", "end": "2026-07-05T18:00:00Z" }
    ]
  },
  {
    "title": "🏎️ GP de Bélgica, Spa-Francorchamps",
    "location": "Circuit de Spa-Francorchamps, Stavelot, Belgium",
    "geo_lat": 50.4372,
    "geo_lon": 5.9714,
    "url": "https://www.formula1.com/en/racing/2026/Belgium.html",
    "broadcasters": ["DAZN F1", "Movistar+"],
    "categories": ["F1", "Motorsport", "Classic"],
    "status": "CONFIRMED",
    "description": "Ronda 12. Eau Rouge y Raidillon en el circuito más largo del calendario.",
    "sessions": [
      { "name": "P1", "start": "2026-07-17T13:30:00Z", "end": "2026-07-17T14:30:00Z" },
      { "name": "P2", "start": "2026-07-17T17:00:00Z", "end": "2026-07-17T18:00:00Z" },
      { "name": "P3", "start": "2026-07-18T12:30:00Z", "end": "2026-07-18T13:30:00Z" },
      { "name": "Qualy", "start": "2026-07-18T16:00:00Z", "end": "2026-07-18T17:00:00Z" },
      { "name": "Carrera", "start": "2026-07-19T15:00:00Z", "end": "2026-07-19T17:00:00Z" }
    ]
  },
  {
    "title": "🏎️ GP de Hungría, Budapest",
    "location": "Hungaroring, Mogyoród, Hungary",
    "geo_lat": 47.5830,
    "geo_lon": 19.2486,
    "url": "https://www.formula1.com/en/racing/2026/Hungary.html",
    "broadcasters": ["DAZN F1", "Movistar+"],
    "categories": ["F1", "Motorsport"],
    "status": "CONFIRMED",
    "description": "Ronda 13. El 'Mónaco sin muros', técnico y exigente.",
    "sessions": [
        { "name": "P1", "start": "2026-07-24T13:30:00Z", "end": "2026-07-24T14:30:00Z" },
        { "name": "P2", "start": "2026-07-24T17:00:00Z", "end": "2026-07-24T18:00:00Z" },
        { "name": "P3", "start": "2026-07-25T12:30:00Z", "end": "2026-07-25T13:30:00Z" },
        { "name": "Qualy", "start": "2026-07-25T16:00:00Z", "end": "2026-07-25T17:00:00Z" },
        { "name": "Carrera", "start": "2026-07-26T15:00:00Z", "end": "2026-07-26T17:00:00Z" }
    ]
  },
  {
    "title": "🏎️ GP de Países Bajos, Zandvoort - Sprint",
    "location": "Circuit Zandvoort, Zandvoort, Netherlands",
    "geo_lat": 52.3888,
    "geo_lon": 4.5409,
    "url": "https://www.formula1.com/en/racing/2026/Netherlands.html",
    "broadcasters": ["DAZN F1", "Movistar+"],
    "categories": ["F1", "Sprint", "Motorsport"],
    "status": "CONFIRMED",
    "description": "Ronda 14. Curvas peraltadas y ambiente naranja junto a la playa.",
    "sessions": [
      { "name": "P1", "start": "2026-08-21T12:30:00Z", "end": "2026-08-21T13:30:00Z" },
      { "name": "Sprint Qualifying", "start": "2026-08-21T16:30:00Z", "end": "2026-08-21T17:14:00Z" },
      { "name": "Sprint", "start": "2026-08-22T12:00:00Z", "end": "2026-08-22T13:00:00Z" },
      { "name": "Qualy", "start": "2026-08-22T16:00:00Z", "end": "2026-08-22T17:00:00Z" },
      { "name": "Carrera", "start": "2026-08-23T15:00:00Z", "end": "2026-08-23T17:00:00Z" }
    ]
  },
  {
    "title": "🏎️ GP de Italia, Monza",
    "location": "Autodromo Nazionale Monza, Monza, Italy",
    "geo_lat": 45.6156,
    "geo_lon": 9.2811,
    "url": "https://www.formula1.com/en/racing/2026/Italy.html",
    "broadcasters": ["DAZN F1", "Movistar+"],
    "categories": ["F1", "Motorsport", "Classic"],
    "status": "CONFIRMED",
    "description": "Ronda 15. El Templo de la Velocidad.",
    "sessions": [
      { "name": "P1", "start": "2026-09-04T12:30:00Z", "end": "2026-09-04T13:30:00Z" },
      { "name": "P2", "start": "2026-09-04T16:00:00Z", "end": "2026-09-04T17:00:00Z" },
      { "name": "P3", "start": "2026-09-05T12:30:00Z", "end": "2026-09-05T13:30:00Z" },
      { "name": "Qualy", "start": "2026-09-05T16:00:00Z", "end": "2026-09-05T17:00:00Z" },
      { "name": "Carrera", "start": "2026-09-06T15:00:00Z", "end": "2026-09-06T17:00:00Z" }
    ]
  },
  {
    "title": "🏎️ GP de Madrid, Madrid",
    "location": "IFEMA Madrid Circuit, Madrid, Spain",
    "geo_lat": 40.4717,
    "geo_lon": -3.6152,
    "url": "https://www.formula1.com/en/racing/2026/Spain.html",
    "broadcasters": ["DAZN F1", "Movistar+"],
    "categories": ["F1", "Motorsport", "New"],
    "status": "CONFIRMED",
    "description": "Ronda 16. ¡Estreno! Nuevo circuito semi-urbano en IFEMA.",
    "sessions": [
      { "name": "P1", "start": "2026-09-11T13:30:00Z", "end": "2026-09-11T14:30:00Z" },
      { "name": "P2", "start": "2026-09-11T17:00:00Z", "end": "2026-09-11T18:00:00Z" },
      { "name": "P3", "start": "2026-09-12T12:30:00Z", "end": "2026-09-12T13:30:00Z" },
      { "name": "Qualy", "start": "2026-09-12T16:00:00Z", "end": "2026-09-12T17:00:00Z" },
      { "name": "Carrera", "start": "2026-09-13T15:00:00Z", "end": "2026-09-13T17:00:00Z" }
    ]
  },
  {
    "title": "🏎️ GP Azerbaiyán, Bakú",
    "location": "Baku City Circuit, Baku, Azerbaijan",
    "geo_lat": 40.3725,
    "geo_lon": 49.8533,
    "url": "https://www.formula1.com/en/racing/2026/Azerbaijan.html",
    "broadcasters": ["DAZN F1", "Movistar+"],
    "categories": ["F1", "Motorsport"],
    "status": "CONFIRMED",
    "description": "Ronda 17. Rectas interminables y la sección del castillo.",
    "sessions": [
      { "name": "P1", "start": "2026-09-25T10:30:00Z", "end": "2026-09-25T11:30:00Z" },
      { "name": "P2", "start": "2026-09-25T14:00:00Z", "end": "2026-09-25T15:00:00Z" },
      { "name": "P3", "start": "2026-09-26T10:30:00Z", "end": "2026-09-26T11:30:00Z" },
      { "name": "Qualy", "start": "2026-09-26T14:00:00Z", "end": "2026-09-26T15:00:00Z" },
      { "name": "Carrera", "start": "2026-09-27T13:00:00Z", "end": "2026-09-27T15:00:00Z" }
    ]
  },
  {
    "title": "🏎️ GP de Singapur, Singapur - Sprint",
    "location": "Marina Bay Street Circuit, Singapore",
    "geo_lat": 1.2914,
    "geo_lon": 103.8640,
    "url": "https://www.formula1.com/en/racing/2026/Singapore.html",
    "broadcasters": ["DAZN F1", "Movistar+"],
    "categories": ["F1", "Sprint", "Motorsport"],
    "status": "CONFIRMED",
    "description": "Ronda 18. La carrera original nocturna, prueba física extrema.",
    "sessions": [
      { "name": "P1", "start": "2026-10-09T10:30:00Z", "end": "2026-10-09T11:30:00Z" },
      { "name": "Sprint Qualy", "start": "2026-10-09T14:30:00Z", "end": "2026-10-09T15:14:00Z" },
      { "name": "Sprint", "start": "2026-10-10T11:00:00Z", "end": "2026-10-10T12:00:00Z" },
      { "name": "Qualy", "start": "2026-10-10T15:00:00Z", "end": "2026-10-10T16:00:00Z" },
      { "name": "Carrera", "start": "2026-10-11T14:00:00Z", "end": "2026-10-11T16:00:00Z" }
    ]
  },
  {
    "title": "🏎️ GP de Estados Unidos, Austin",
    "location": "Circuit of The Americas, Austin, USA",
    "geo_lat": 30.1328,
    "geo_lon": -97.6411,
    "url": "https://www.formula1.com/en/racing/2026/United-States.html",
    "broadcasters": ["DAZN F1", "Movistar+"],
    "categories": ["F1", "Motorsport"],
    "status": "CONFIRMED",
    "description": "Ronda 19. Desniveles y la icónica subida a la curva 1.",
    "sessions": [
      { "name": "P1", "start": "2026-10-23T19:30:00Z", "end": "2026-10-23T20:30:00Z" },
      { "name": "P2", "start": "2026-10-23T23:00:00Z", "end": "2026-10-24T00:00:00Z" },
      { "name": "P3", "start": "2026-10-24T19:30:00Z", "end": "2026-10-24T20:30:00Z" },
      { "name": "Qualy", "start": "2026-10-24T23:00:00Z", "end": "2026-10-25T00:00:00Z" },
      { "name": "Carrera", "start": "2026-10-25T21:00:00Z", "end": "2026-10-25T23:00:00Z" }
    ]
  },
  {
    "title": "🏎️ GP de Ciudad de México, CDMX",
    "location": "Autódromo Hermanos Rodríguez, Mexico City, Mexico",
    "geo_lat": 19.4042,
    "geo_lon": -99.0907,
    "url": "https://www.formula1.com/en/racing/2026/Mexico.html",
    "broadcasters": ["DAZN F1", "Movistar+"],
    "categories": ["F1", "Motorsport"],
    "status": "CONFIRMED",
    "description": "Ronda 20. La fiesta en el Foro Sol a más de 2000m de altura.",
    "sessions": [
      { "name": "P1", "start": "2026-10-30T19:30:00Z", "end": "2026-10-30T20:30:00Z" },
      { "name": "P2", "start": "2026-10-30T23:00:00Z", "end": "2026-10-31T00:00:00Z" },
      { "name": "P3", "start": "2026-10-31T18:30:00Z", "end": "2026-10-31T19:30:00Z" },
      { "name": "Qualy", "start": "2026-10-31T22:00:00Z", "end": "2026-10-31T23:00:00Z" },
      { "name": "Carrera", "start": "2026-11-01T21:00:00Z", "end": "2026-11-01T23:00:00Z" }
    ]
  },
  {
    "title": "🏎️ GP de Brasil, São Paulo",
    "location": "Autódromo de Interlagos, São Paulo, Brazil",
    "geo_lat": -23.7036,
    "geo_lon": -46.6997,
    "url": "https://www.formula1.com/en/racing/2026/Brazil.html",
    "broadcasters": ["DAZN F1", "Movistar+"],
    "categories": ["F1", "Motorsport", "Classic"],
    "status": "CONFIRMED",
    "description": "Ronda 21. Clima impredecible y la 'S' de Senna.",
    "sessions": [
      { "name": "P1", "start": "2026-11-06T16:30:00Z", "end": "2026-11-06T17:30:00Z" },
      { "name": "P2", "start": "2026-11-06T20:00:00Z", "end": "2026-11-06T21:00:00Z" },
      { "name": "P3", "start": "2026-11-07T15:30:00Z", "end": "2026-11-07T16:30:00Z" },
      { "name": "Qualy", "start": "2026-11-07T19:00:00Z", "end": "2026-11-07T20:00:00Z" },
      { "name": "Carrera", "start": "2026-11-08T18:00:00Z", "end": "2026-11-08T20:00:00Z" }
    ]
  },
  {
    "title": "🏎️ GP de Las Vegas, Las Vegas",
    "location": "Las Vegas Strip Circuit, Las Vegas, USA",
    "geo_lat": 36.1147,
    "geo_lon": -115.1728,
    "url": "https://www.formula1.com/en/racing/2026/Las-Vegas.html",
    "broadcasters": ["DAZN F1", "Movistar+"],
    "categories": ["F1", "Motorsport"],
    "status": "CONFIRMED",
    "description": "Ronda 22. A fondo por el Strip de Las Vegas.",
    "sessions": [
      { "name": "P1", "start": "2026-11-20T01:30:00Z", "end": "2026-11-20T02:30:00Z" },
      { "name": "P2", "start": "2026-11-20T05:00:00Z", "end": "2026-11-20T06:00:00Z" },
      { "name": "P3", "start": "2026-11-21T01:30:00Z", "end": "2026-11-21T02:30:00Z" },
      { "name": "Qualy", "start": "2026-11-21T05:00:00Z", "end": "2026-11-21T06:00:00Z" },
      { "name": "Carrera", "start": "2026-11-22T05:00:00Z", "end": "2026-11-22T07:00:00Z" }
    ]
  },
  {
    "title": "🏎️ GP de Qatar, Lusail",
    "location": "Lusail International Circuit, Lusail, Qatar",
    "geo_lat": 25.4888,
    "geo_lon": 51.4542,
    "url": "https://www.formula1.com/en/racing/2026/Qatar.html",
    "broadcasters": ["DAZN F1", "Movistar+"],
    "categories": ["F1", "Motorsport"],
    "status": "CONFIRMED",
    "description": "Ronda 23. Penúltima cita en el desierto catarí.",
    "sessions": [
      { "name": "P1", "start": "2026-11-27T14:30:00Z", "end": "2026-11-27T15:30:00Z" },
      { "name": "P2", "start": "2026-11-27T18:00:00Z", "end": "2026-11-27T19:00:00Z" },
      { "name": "P3", "start": "2026-11-28T15:30:00Z", "end": "2026-11-28T16:30:00Z" },
      { "name": "Qualy", "start": "2026-11-28T19:00:00Z", "end": "2026-11-28T20:00:00Z" },
      { "name": "Carrera", "start": "2026-11-29T17:00:00Z", "end": "2026-11-29T19:00:00Z" }
    ]
  },
  {
    "title": "🏎️ GP de Abu Dabi, Yas Marina",
    "location": "Yas Marina Circuit, Abu Dhabi, UAE",
    "geo_lat": 24.4672,
    "geo_lon": 54.6031,
    "url": "https://www.formula1.com/en/racing/2026/united-arab-emirates.html",
    "broadcasters": ["DAZN F1", "Movistar+"],
    "categories": ["F1", "Motorsport", "Finale"],
    "status": "CONFIRMED",
    "description": "Ronda 24. La gran final de la temporada.",
    "sessions": [
      { "name": "P1", "start": "2026-12-04T10:30:00Z", "end": "2026-12-04T11:30:00Z" },
      { "name": "P2", "start": "2026-12-04T14:00:00Z", "end": "2026-12-04T15:00:00Z" },
      { "name": "P3", "start": "2026-12-05T11:30:00Z", "end": "2026-12-05T12:30:00Z" },
      { "name": "Qualy", "start": "2026-12-05T15:00:00Z", "end": "2026-12-05T16:00:00Z" },
      { "name": "Carrera", "start": "2026-12-06T14:00:00Z", "end": "2026-12-06T16:00:00Z" }
    ]
  },
  {
    "title": "🏁 GT Round 1: Circuit Paul Ricard",
    "location": "Circuit Paul Ricard, Le Castellet, France",
    "geo_lat": 43.2506,
    "geo_lon": 5.7917,
    "url": "https://www.gt-world-challenge-europe.com/",
    "broadcasters": ["GTWorld YouTube", "Eurosport"],
    "categories": ["GT", "Endurance", "Motorsport"],
    "status": "CONFIRMED",
    "description": "Inicio de temporada GT World Challenge Europe.",
    "sessions": [
      { "name": "Lamborghini Super Trofeo - Qualifying", "start": "2026-04-11T09:00:00Z", "end": "2026-04-11T09:50:00Z" },
      { "name": "GT4 European Series - Pre-Qualifying", "start": "2026-04-11T10:00:00Z", "end": "2026-04-11T11:00:00Z" },
      { "name": "GT3 Revival Series - Pre-Qualifying", "start": "2026-04-11T11:10:00Z", "end": "2026-04-11T11:55:00Z" },
      { "name": "GT World - Qualifying", "start": "2026-04-11T12:05:00Z", "end": "2026-04-11T13:05:00Z" },
      { "name": "Lamborghini Super Trofeo - Race 1", "start": "2026-04-11T14:40:00Z", "end": "2026-04-11T15:30:00Z" },
      { "name": "GT4 European Series - Qualifying", "start": "2026-04-11T15:45:00Z", "end": "2026-04-11T16:30:00Z" },
      { "name": "GT3 Revival Series - Qualifying", "start": "2026-04-11T16:40:00Z", "end": "2026-04-11T17:15:00Z" },
      { "name": "GT World - Race", "start": "2026-04-11T18:00:00Z", "end": "2026-04-12T00:00:00Z" },
      { "name": "GT3 Revival Series - Race 1", "start": "2026-04-12T09:30:00Z", "end": "2026-04-12T10:20:00Z" },
      { "name": "GT4 European Series - Race 1", "start": "2026-04-12T11:00:00Z", "end": "2026-04-12T12:00:00Z" },
      { "name": "Lamborghini Super Trofeo - Race 2", "start": "2026-04-12T12:30:00Z", "end": "2026-04-12T13:20:00Z" },
      { "name": "GT3 Revival Series - Race 2", "start": "2026-04-12T15:00:00Z", "end": "2026-04-12T15:50:00Z" },
      { "name": "GT4 European Series - Race 2", "start": "2026-04-12T16:30:00Z", "end": "2026-04-12T17:30:00Z" }
    ]
  },
  {
    "title": "🏁 GT Round 2: Brands Hatch",
    "location": "Brands Hatch, Kent, UK",
    "geo_lat": 51.3569,
    "geo_lon": 0.2630,
    "url": "https://www.gt-world-challenge-europe.com/",
    "broadcasters": ["GTWorld YouTube", "Eurosport"],
    "categories": ["GT", "Sprint", "Motorsport"],
    "status": "CONFIRMED",
    "description": "Acción rápida en el mítico circuito británico.",
    "sessions": [
      { "name": "Radical Cup UK - Qualifying", "start": "2026-05-02T10:00:00Z", "end": "2026-05-02T10:25:00Z" },
      { "name": "GT World - Free Practice 1", "start": "2026-05-02T10:35:00Z", "end": "2026-05-02T11:35:00Z" },
      { "name": "Miata Trophy - Qualifying", "start": "2026-05-02T11:45:00Z", "end": "2026-05-02T12:00:00Z" },
      { "name": "Legends Cars Championship - Practice", "start": "2026-05-02T12:10:00Z", "end": "2026-05-02T12:20:00Z" },
      { "name": "Sport 2000 Championship - Qualifying", "start": "2026-05-02T12:30:00Z", "end": "2026-05-02T12:50:00Z" },
      { "name": "GT World - Free Practice 2", "start": "2026-05-02T13:00:00Z", "end": "2026-05-02T14:00:00Z" },
      { "name": "Legends Cars - Race 1", "start": "2026-05-02T14:10:00Z", "end": "2026-05-02T14:20:00Z" },
      { "name": "Miata Trophy - Race 1", "start": "2026-05-02T15:00:00Z", "end": "2026-05-02T15:20:00Z" },
      { "name": "Radical Cup UK - Race 1", "start": "2026-05-02T15:35:00Z", "end": "2026-05-02T16:25:00Z" },
      { "name": "Legends Cars - Race 2", "start": "2026-05-02T16:40:00Z", "end": "2026-05-02T16:50:00Z" },
      { "name": "Sport 2000 Championship - Race 1", "start": "2026-05-02T17:05:00Z", "end": "2026-05-02T17:30:00Z" },
      { "name": "GT World - Qualifying", "start": "2026-05-02T17:40:00Z", "end": "2026-05-02T18:15:00Z" },
      { "name": "Miata Trophy - Race 2", "start": "2026-05-02T18:30:00Z", "end": "2026-05-02T18:50:00Z" },
      { "name": "Legends Cars - Race 3", "start": "2026-05-02T19:05:00Z", "end": "2026-05-02T19:20:00Z" },
      { "name": "750MC Roadsports - Qualifying", "start": "2026-05-03T11:00:00Z", "end": "2026-05-03T11:25:00Z" },
      { "name": "GT World - Race 1", "start": "2026-05-03T12:15:00Z", "end": "2026-05-03T13:15:00Z" },
      { "name": "Legends Cars - Race 4", "start": "2026-05-03T13:25:00Z", "end": "2026-05-03T13:35:00Z" },
      { "name": "Radical Cup UK - Race 2", "start": "2026-05-03T13:45:00Z", "end": "2026-05-03T14:35:00Z" },
      { "name": "Sport 2000 Championship - Race 2", "start": "2026-05-03T15:15:00Z", "end": "2026-05-03T15:40:00Z" },
      { "name": "Legends Cars - Race 5", "start": "2026-05-03T15:50:00Z", "end": "2026-05-03T16:00:00Z" },
      { "name": "GT World - Race 2", "start": "2026-05-03T16:45:00Z", "end": "2026-05-03T17:45:00Z" },
      { "name": "750MC Roadsports - Race 1", "start": "2026-05-03T18:00:00Z", "end": "2026-05-03T18:45:00Z" },
      { "name": "Legends Cars - Race 6", "start": "2026-05-03T19:00:00Z", "end": "2026-05-03T19:15:00Z" }
    ]
  },
  {
    "title": "🏁 GT Prologue: 24h of Spa",
    "location": "Circuit de Spa-Francorchamps, Stavelot, Belgium",
    "geo_lat": 50.4372,
    "geo_lon": 5.9714,
    "start": "2026-05-19T08:00:00Z",
    "end": "2026-05-20T16:00:00Z",
    "broadcasters": ["GTWorld YouTube"],
    "categories": ["GT", "Test"],
    "status": "CONFIRMED",
    "url": "https://www.crowdstrike24hoursofspa.com/",
    "description": "Test oficial previo a las 24h de Spa."
  },
  {
    "title": "🏁 GT Round 3: Monza",
    "location": "Autodromo Nazionale Monza, Monza, Italy",
    "geo_lat": 45.6156,
    "geo_lon": 9.2811,
    "start": "2026-05-30T00:00:00Z",
    "end": "2026-05-31T23:59:00Z",
    "broadcasters": ["GTWorld YouTube", "Eurosport"],
    "categories": ["GT", "Endurance"],
    "status": "CONFIRMED",
    "url": "https://www.gt-world-challenge-europe.com/",
    "description": "Resistencia en el Templo de la Velocidad."
  },
  {
    "title": "🏁 GT Round 4: 24h of Spa",
    "location": "Circuit de Spa-Francorchamps, Stavelot, Belgium",
    "geo_lat": 50.4372,
    "geo_lon": 5.9714,
    "start": "2026-06-25T00:00:00Z",
    "end": "2026-06-28T23:59:00Z",
    "broadcasters": ["GTWorld YouTube", "Eurosport"],
    "categories": ["GT", "Endurance", "Classic"],
    "status": "CONFIRMED",
    "url": "https://www.crowdstrike24hoursofspa.com/",
    "description": "La carrera de GT más importante del mundo."
  },
  {
    "title": "🏁 GT Round 5: Misano",
    "location": "Misano World Circuit, Misano Adriatico, Italy",
    "geo_lat": 43.9625,
    "geo_lon": 12.6843,
    "start": "2026-07-18T00:00:00Z",
    "end": "2026-07-19T23:59:00Z",
    "broadcasters": ["GTWorld YouTube", "Eurosport"],
    "categories": ["GT", "Sprint"],
    "status": "CONFIRMED",
    "url": "https://www.gt-world-challenge-europe.com/",
    "description": "Carreras Sprint bajo el sol italiano."
  },
  {
    "title": "🏁 GT Round 6: Magny-Cours",
    "location": "Circuit de Nevers Magny-Cours, France",
    "geo_lat": 46.8642,
    "geo_lon": 3.1636,
    "start": "2026-08-01T00:00:00Z",
    "end": "2026-08-02T23:59:00Z",
    "broadcasters": ["GTWorld YouTube", "Eurosport"],
    "categories": ["GT", "Sprint"],
    "status": "CONFIRMED",
    "url": "https://www.gt-world-challenge-europe.com/",
    "description": "Técnica y velocidad en suelo francés."
  },
  {
    "title": "🏁 GT Round 7: Nürburgring",
    "location": "Nürburgring GP Strecke, Nürburg, Germany",
    "geo_lat": 50.3356,
    "geo_lon": 6.9475,
    "start": "2026-08-29T00:00:00Z",
    "end": "2026-08-30T23:59:00Z",
    "broadcasters": ["GTWorld YouTube", "Eurosport"],
    "categories": ["GT", "Endurance"],
    "status": "CONFIRMED",
    "url": "https://www.gt-world-challenge-europe.com/",
    "description": "Resistencia en el corazón de Eifel."
  },
  {
    "title": "🏁 GT Round 8: Zandvoort",
    "location": "Circuit Zandvoort, Zandvoort, Netherlands",
    "geo_lat": 52.3888,
    "geo_lon": 4.5409,
    "start": "2026-09-19T00:00:00Z",
    "end": "2026-09-20T23:59:00Z",
    "broadcasters": ["GTWorld YouTube", "Eurosport"],
    "categories": ["GT", "Sprint"],
    "status": "CONFIRMED",
    "url": "https://www.gt-world-challenge-europe.com/",
    "description": "Sprint entre las dunas."
  },
  {
    "title": "🏁 GT Round 9: Barcelona",
    "location": "Circuit de Barcelona-Catalunya, Montmeló, Spain",
    "geo_lat": 41.5700,
    "geo_lon": 2.2611,
    "start": "2026-10-03T00:00:00Z",
    "end": "2026-10-04T23:59:00Z",
    "broadcasters": ["GTWorld YouTube", "Eurosport"],
    "categories": ["GT", "Sprint", "Finale"],
    "status": "CONFIRMED",
    "url": "https://www.gt-world-challenge-europe.com/",
    "description": "Final de la Copa Sprint."
  },
  {
    "title": "🏁 GT Round 10: Portimao",
    "location": "Algarve International Circuit, Portimão, Portugal",
    "geo_lat": 37.2312,
    "geo_lon": -8.6283,
    "start": "2026-10-17T00:00:00Z",
    "end": "2026-10-18T23:59:00Z",
    "broadcasters": ["GTWorld YouTube", "Eurosport"],
    "categories": ["GT", "Endurance"],
    "status": "CONFIRMED",
    "url": "https://www.gt-world-challenge-europe.com/",
    "description": "Montaña rusa para cerrar la temporada."
  }
]